Workbook

Sheet Питання
A1: Конфігурація | B1: Лекція | C1: ID | D1: Цільовий рівень Блума | E1: Статус Критика | F1: Питання | G1: Ключ | H1: Дистрактор 1 | I1: Дистрактор 2 | J1: Дистрактор 3 | K1: F | L1: A | M1: P | N1: S | O1: Сума | P1: Прийнято | Q1: Вирішувач обрав ключ | R1: Рівень Блума (арбітр) | S1: Збіг рівня Блума | T1: CV слів | U1: CV символів | V1: Ключ найдовший | W1: Середній косинус | X1: Коментар арбітра
A2: M1 | B2: W01 | C2: b00_0 | D2: 1 | E2: m1_generated | F2: Що таке framework? | G2: Каркас для програми, що включає набір інструментів, бібліотек, модулів та методологію | H2: Мова програмування для створення веб-додатків | I2: Система управління базами даних | J2: Графічний редактор для дизайну інтерфейсів | K2: 1 | L2: 1 | M2: 1 | N2: 0 | O2: 3 | P2: 0 | Q2: 1 | R2: 1 | S2: 1 | T2: 0.444 | U2: 0.403 | V2: 1 | W2: 0.464 | X2: Знижено: No_Shortcuts=0 (ключ 11 слів проти 4.67 у дистракторів). Коментар моделі: Фактологічно ключ коректний: framework — це дійсно каркас/платформа, що включає набір інструментів, бібліотек, модулів та методологію розробки. Усі три дистрактори однозначно хибні та правдоподібні: мова програмування, СУБД і графічний редактор — реальні поняття зі сфери ІТ, які студент-початківець може сплутати з framework. Однак no_shortcuts_score = 0: ключ (11 слів) помітно довший за дистрактори (середня 4.67 слова), що автоматично виділяє його серед варіантів і є підказкою. Дистрактори слід розширити до порівнянної довжини або скоротити ключ.
A3: M1 | B3: W01 | C3: b00_1 | D3: 1 | E3: m1_generated | F3: Хто створив Laravel і в якому році? | G3: Тейлор Отвел у 2011 році | H3: Брендан Айх у 1995 році | I3: Джеймс Гослінг у 1995 році | J3: Расмус Лердорф у 1994 році | K3: 1 | L3: 1 | M3: 1 | N3: 1 | O3: 4 | P3: 1 | Q3: 1 | R3: 1 | S3: 1 | T3: 0 | U3: 0.052 | V3: 0 | W3: 0.232 | X3: Ключ фактологічно коректний: Laravel створив Тейлор Отвел у 2011 році. Дистрактори правдоподібні — Брендан Айх (JavaScript, 1995), Джеймс Гослінг (Java, 1995), Расмус Лердорф (PHP, 1994) — реальні постаті зі суміжної галузі (мови програмування та веб-технології), яких студент міг би сплутати. Усі дистрактори однозначно хибні. Довжина варіантів однорідна. Підказок немає.
A4: M1 | B4: W01 | C4: b00_10 | D4: 3 | E4: m1_generated | F4: Який інструмент Laravel дозволяє створювати динамічні інтерфейси виключно на PHP без написання JavaScript? | G4: Livewire | H4: Inertia.js | I4: Vue.js | J4: React | K4: 1 | L4: 1 | M4: 1 | N4: 1 | O4: 4 | P4: 1 | Q4: 1 | R4: 1 | S4: 0 | T4: 0 | U4: 0.265 | V4: 0 | W4: 0.182 | X4: Усі критерії виконано бездоганно. Livewire — це дійсно інструмент екосистеми Laravel, що дозволяє будувати динамічні інтерфейси виключно на PHP без написання JavaScript. Дистрактори правдоподібні: Inertia.js — суміжний інструмент Laravel-екосистеми, але потребує JS-компонентів; Vue.js і React — популярні JS-фреймворки, які часто використовуються з Laravel. Усі варіанти однорідні за форматом і довжиною. Підказок немає.
A5: M1 | B5: W01 | C5: b00_11 | D5: 3 | E5: m1_generated | F5: Яка команда Artisan використовується для очищення всього кешу (роутів, конфігів, шаблонів)? | G5: php artisan optimize:clear | H5: php artisan cache:clear | I5: php artisan config:clear | J5: php artisan route:clear | K5: 1 | L5: 1 | M5: 1 | N5: 1 | O5: 4 | P5: 1 | Q5: 1 | R5: 1 | S5: 0 | T5: 0 | U5: 0.051 | V5: 1 | W5: 0.734 | X5: Ключ `php artisan optimize:clear` є фактично коректним: ця команда Laravel очищає кеш роутів, конфігурацій, скомпільованих шаблонів, загального кешу та bootstrap-файлів одночасно. Усі три дистрактори є реальними Artisan-командами, що очищають лише окремий тип кешу, тому вони правдоподібні, але однозначно хибні в контексті запитання про «все». Довжина варіантів однакова, підказок немає, формат однорідний.
A6: M1 | B6: W01 | C6: b00_2 | D6: 1 | E6: m1_generated | F6: Який файл є єдиною точкою входу для всіх запитів у Laravel? | G6: public/index.php | H6: routes/web.php | I6: app/Http/Kernel.php | J6: bootstrap/app.php | K6: 1 | L6: 1 | M6: 1 | N6: 1 | O6: 4 | P6: 1 | Q6: 1 | R6: 1 | S6: 1 | T6: 0 | U6: 0.109 | V6: 0 | W6: 0.442 | X6: Усі критерії виконано бездоганно. public/index.php є загальновідомою єдиною точкою входу (front controller) у Laravel — це задокументований факт. Дистрактори правдоподібні: routes/web.php — файл маршрутів, app/Http/Kernel.php — HTTP-ядро, bootstrap/app.php — файл ініціалізації застосунку; всі три є реальними файлами Laravel, які студент міг би сплутати з точкою входу. Варіанти однорідні за форматом (шляхи до файлів), довжина приблизно однакова, підказок немає.
A7: M1 | B7: W01 | C7: b00_3 | D7: 1 | E7: m1_generated | F7: Яка команда Artisan використовується для запуску вбудованого сервера розробки? | G7: php artisan serve | H7: php artisan migrate | I7: php artisan make:controller | J7: php artisan tinker | K7: 1 | L7: 1 | M7: 1 | N7: 1 | O7: 4 | P7: 1 | Q7: 1 | R7: 1 | S7: 1 | T7: 0 | U7: 0.196 | V7: 0 | W7: 0.752 | X7: Усі критерії виконано бездоганно. Команда `php artisan serve` є стандартною командою Laravel для запуску вбудованого сервера розробки — фактологічно коректно. Дистрактори однозначно хибні: `migrate` — для міграцій БД, `make:controller` — для генерації контролера, `tinker` — для інтерактивної консолі REPL. Усі дистрактори правдоподібні, належать до тієї ж галузі (Artisan CLI Laravel) і є реальними командами, які студент міг би сплутати. Довжина варіантів однорідна (3 слова кожен), підказок немає.
A8: M1 | B8: W01 | C8: b00_4 | D8: 2 | E8: m1_generated | F8: Яка перевага Laravel перед «чистим PHP»? | G8: Код структурований, що робить його зрозумілим іншим розробникам | H8: Laravel не потребує знання PHP | I8: Laravel працює лише на Windows | J8: Laravel автоматично створює базу даних без SQL | K8: 1 | L8: 0 | M8: 1 | N8: 0 | O8: 2 | P8: 0 | Q8: 1 | R8: 1 | S8: 0 | T8: 0.208 | U8: 0.323 | V8: 1 | W8: -0.007 | X8: Знижено: No_Ambiguity=0; No_Shortcuts=0 (ключ 8 слів проти 5.67 у дистракторів; неоднорідний формат варіантів: KEY, D1, D2, D3). Коментар моделі: Фактологічно ключ коректний: Laravel як MVC-фреймворк справді структурує код і полегшує командну роботу. Дистрактори правдоподібні в межах теми (хибні, але типові помилкові уявлення про фреймворки). Однак є два дефекти. 1) no_shortcuts_score = 0: ключ помітно довший за дистрактори (8 слів проти середніх 5.67), що саме по собі є підказкою. 2) ambiguity_score = 0 через два порушення: (а) неоднорідність формату — слово «Laravel» (латиниця) присутнє в D1, D2, D3, але відсутнє в ключі, що виділяє ключ серед варіантів; (б) D2 містить категоричне слово «лише» у категоричному значенні, тоді як ключ його не містить — це додаткова підказка. Також D2 є очевидно хибним фактом (Laravel підтримує будь-яку ОС), що знижує конкурентність, але не виводить дистрактор за межі галузі.
A9: M1 | B9: W01 | C9: b00_5 | D9: 2 | E9: m1_generated | F9: Який компонент Laravel реалізує шаблон ActiveRecord для роботи з базою даних? | G9: Eloquent ORM | H9: Blade | I9: Artisan | J9: Composer | K9: 1 | L9: 1 | M9: 1 | N9: 1 | O9: 4 | P9: 1 | Q9: 1 | R9: 1 | S9: 0 | T9: 0.346 | U9: 0.319 | V9: 1 | W9: 0.252 | X9: Усі критерії виконано бездоганно. Eloquent ORM дійсно реалізує шаблон ActiveRecord у Laravel — загальновідомий факт. Дистрактори: Blade — шаблонізатор, Artisan — CLI-інструмент, Composer — менеджер залежностей PHP (не компонент Laravel, але тісно пов'язаний з екосистемою); усі три є правдоподібними поняттями з тієї самої галузі (PHP/Laravel-розробка) і однозначно хибними в контексті запитання. Довжина варіантів відносно однорідна (ключ — 2 слова, дистрактори — по 1 слову), суттєвої підказки немає. Мовних помилок не виявлено.
A10: M1 | B10: W01 | C10: b00_6 | D10: 2 | E10: m1_generated | F10: Що таке Composer у контексті Laravel? | G10: Менеджер пакетів для встановлення та підключення залежностей | H10: Вбудований веб-сервер | I10: Шаблонізатор для HTML | J10: Система контролю версій | K10: 1 | L10: 1 | M10: 1 | N10: 0 | O10: 3 | P10: 0 | Q10: 1 | R10: 1 | S10: 0 | T10: 0.512 | U10: 0.532 | V10: 1 | W10: 0.279 | X10: Знижено: No_Shortcuts=0 (ключ 7 слів проти 2.67 у дистракторів). Коментар моделі: Фактологічно ключ коректний: Composer — менеджер залежностей (пакетів) для PHP/Laravel. Усі три дистрактори хибні й правдоподібні: вбудований веб-сервер (Artisan serve), шаблонізатор (Blade) та система контролю версій (Git) — реальні поняття зі сфери веб-розробки, які студент може сплутати. Однак no_shortcuts_score = 0: ключ містить 7 слів, тоді як середня довжина дистракторів — лише 2.67 слова, що є помітною підказкою. Неоднорідність формату: у D2 вжито латиницю («HTML»), тоді як в інших варіантах латиниці немає — проте це одна абревіатура, яка є загальновживаною і не виділяє варіант як підказку; format_mismatch не фіксується.
A11: M1 | B11: W01 | C11: b00_7 | D11: 2 | E11: m1_generated | F11: Який файл у Laravel містить налаштування локального середовища, такі як паролі та ключі? | G11: .env | H11: config/app.php | I11: composer.json | J11: package.json | K11: 1 | L11: 1 | M11: 1 | N11: 1 | O11: 4 | P11: 1 | Q11: 1 | R11: 1 | S11: 0 | T11: 0 | U11: 0.368 | V11: 0 | W11: 0.244 | X11: Усі критерії виконано бездоганно. Файл .env у Laravel є стандартним місцем зберігання змінних середовища (паролі, ключі API, налаштування БД тощо) — це загальновідомий факт. Дистрактори правдоподібні: config/app.php містить деякі налаштування застосунку (але не секрети середовища), composer.json — залежності PHP, package.json — залежності Node.js; усі три є реальними файлами Laravel/PHP-проєкту, які студент міг би сплутати. Довжина варіантів однорідна, підказок немає.
A12: M1 | B12: W01 | C12: b00_8 | D12: 3 | E12: m1_generated | F12: Який етап життєвого циклу запиту в Laravel відповідає за виклик методу контролера? | G12: Маршрутизація (Router) | H12: Точка входу (public/index.php) | I12: Ядро (Kernel) | J12: Відповідь (Response) | K12: 1 | L12: 1 | M12: 1 | N12: 1 | O12: 4 | P12: 1 | Q12: 1 | R12: 1 | S12: 0 | T12: 0.192 | U12: 0.285 | V12: 0 | W12: 0.331 | X12: Усі критерії виконано. Маршрутизатор (Router) у Laravel дійсно відповідає за зіставлення запиту з маршрутом і безпосередній виклик методу контролера — ключ фактологічно коректний. Дистрактори є правдоподібними: public/index.php — точка входу, Kernel — обробляє middleware та передає запит, Response — формує відповідь; усі три є реальними етапами циклу запиту Laravel, але жоден не відповідає за виклик методу контролера. Підказок за довжиною чи форматом немає.
A13: M1 | B13: W01 | C13: b00_9 | D13: 3 | E13: m1_generated | F13: Яка команда Artisan створює модель разом із міграцією? | G13: php artisan make:model Post -m | H13: php artisan make:controller PostController | I13: php artisan migrate | J13: php artisan make:migration create_posts_table | K13: 1 | L13: 1 | M13: 1 | N13: 1 | O13: 4 | P13: 1 | Q13: 1 | R13: 1 | S13: 0 | T13: 0.177 | U13: 0.304 | V13: 0 | W13: 0.681 | X13: Ключ коректний: `php artisan make:model Post -m` (прапорець `-m`/`--migration`) дійсно створює модель разом із міграцією — загальновідомий факт Laravel. Усі дистрактори правдоподібні й однозначно хибні в контексті запитання: D1 створює контролер, D2 запускає міграції, D3 створює лише міграцію без моделі. Довжина варіантів порівнянна, підказок немає.
... A433: M4 | B433: A03 | C433: b11_0 | D433: 1 | E433: passed_at_iter_1 | F433: Який рік видання має стаття Cheng X. «A Comprehensive Study of Feature Selection Techniques in Machine Learning Models»? | G433: 2024 | H433: 2022 | I433: 2021 | J433: 2023 | K433: 1 | L433: 1 | M433: 1 | N433: 1 | O433: 4 | P433: 1 | Q433: 1 | R433: 1 | S433: 1 | T433: 0 | U433: 0 | V433: 0 | W433: 0.889 | X433: Усі оцінки 1. Питання суто бібліографічне: рік публікації конкретної статті не можна вивести з логіки галузі. Ключ 2024 збігається з тим, що експерт пам'ятає (Cheng X., Insights in Computer, Signals and Systems, 2024), тож явних підстав вважати його хибним немає. Дистрактори 2021–2023 — правдоподібні роки з того ж діапазону, однорідні за форматом, однозначно хибні. Довжина і стиль варіантів однакові, категоричних слів немає, посилань на джерело в запитанні немає. Перевірити відповідь можна лише за бібліографічним записом.

Sheet Зведення
A1: Конфігурація | B1: Питань | C1: Прийнято | D1: % прийнято | E1: Factuality % | F1: No_Ambiguity % | G1: Plausibility % | H1: No_Shortcuts % | I1: Середній CV слів | J1: Середній CV символів | K1: Ключ найдовший % | L1: Середній косинус | M1: Збіг Блуму % | N1: Вирішувач обрав ключ %
A2: M1 | B2: =COUNTIF(Питання!$A$2:$A$433,A2) | C2: =SUMIFS(Питання!$P$2:$Q$433,Питання!$A$2:$A$433,A2) | D2: =C2/B2 | E2: =SUMIFS(Питання!$K$2:$L$433,Питання!$A$2:$A$433,A2)/B2 | F2: =SUMIFS(Питання!$L$2:$M$433,Питання!$A$2:$A$433,A2)/B2 | G2: =SUMIFS(Питання!$M$2:$N$433,Питання!$A$2:$A$433,A2)/B2 | H2: =SUMIFS(Питання!$N$2:$O$433,Питання!$A$2:$A$433,A2)/B2 | I2: =AVERAGEIFS(Питання!$T$2:$V$433,Питання!$A$2:$A$433,A2) | J2: =AVERAGEIFS(Питання!$U$2:$W$433,Питання!$A$2:$A$433,A2) | K2: =SUMIFS(Питання!$V$2:$X$433,Питання!$A$2:$A$433,A2)/B2 | L2: =AVERAGEIFS(Питання!$W$2:$Y$433,Питання!$A$2:$A$433,A2) | M2: =SUMIFS(Питання!$S$2:$T$433,Питання!$A$2:$A$433,A2)/B2 | N2: =SUMIFS(Питання!$Q$2:$R$433,Питання!$A$2:$A$433,A2)/B2
A3: M2 | B3: =COUNTIF(Питання!$A$2:$A$433,A3) | C3: =SUMIFS(Питання!$P$2:$Q$433,Питання!$A$2:$A$433,A3) | D3: =C3/B3 | E3: =SUMIFS(Питання!$K$2:$L$433,Питання!$A$2:$A$433,A3)/B3 | F3: =SUMIFS(Питання!$L$2:$M$433,Питання!$A$2:$A$433,A3)/B3 | G3: =SUMIFS(Питання!$M$2:$N$433,Питання!$A$2:$A$433,A3)/B3 | H3: =SUMIFS(Питання!$N$2:$O$433,Питання!$A$2:$A$433,A3)/B3 | I3: =AVERAGEIFS(Питання!$T$2:$V$433,Питання!$A$2:$A$433,A3) | J3: =AVERAGEIFS(Питання!$U$2:$W$433,Питання!$A$2:$A$433,A3) | K3: =SUMIFS(Питання!$V$2:$X$433,Питання!$A$2:$A$433,A3)/B3 | L3: =AVERAGEIFS(Питання!$W$2:$Y$433,Питання!$A$2:$A$433,A3) | M3: =SUMIFS(Питання!$S$2:$T$433,Питання!$A$2:$A$433,A3)/B3 | N3: =SUMIFS(Питання!$Q$2:$R$433,Питання!$A$2:$A$433,A3)/B3
A4: M3 | B4: =COUNTIF(Питання!$A$2:$A$433,A4) | C4: =SUMIFS(Питання!$P$2:$Q$433,Питання!$A$2:$A$433,A4) | D4: =C4/B4 | E4: =SUMIFS(Питання!$K$2:$L$433,Питання!$A$2:$A$433,A4)/B4 | F4: =SUMIFS(Питання!$L$2:$M$433,Питання!$A$2:$A$433,A4)/B4 | G4: =SUMIFS(Питання!$M$2:$N$433,Питання!$A$2:$A$433,A4)/B4 | H4: =SUMIFS(Питання!$N$2:$O$433,Питання!$A$2:$A$433,A4)/B4 | I4: =AVERAGEIFS(Питання!$T$2:$V$433,Питання!$A$2:$A$433,A4) | J4: =AVERAGEIFS(Питання!$U$2:$W$433,Питання!$A$2:$A$433,A4) | K4: =SUMIFS(Питання!$V$2:$X$433,Питання!$A$2:$A$433,A4)/B4 | L4: =AVERAGEIFS(Питання!$W$2:$Y$433,Питання!$A$2:$A$433,A4) | M4: =SUMIFS(Питання!$S$2:$T$433,Питання!$A$2:$A$433,A4)/B4 | N4: =SUMIFS(Питання!$Q$2:$R$433,Питання!$A$2:$A$433,A4)/B4
A5: M4 | B5: =COUNTIF(Питання!$A$2:$A$433,A5) | C5: =SUMIFS(Питання!$P$2:$Q$433,Питання!$A$2:$A$433,A5) | D5: =C5/B5 | E5: =SUMIFS(Питання!$K$2:$L$433,Питання!$A$2:$A$433,A5)/B5 | F5: =SUMIFS(Питання!$L$2:$M$433,Питання!$A$2:$A$433,A5)/B5 | G5: =SUMIFS(Питання!$M$2:$N$433,Питання!$A$2:$A$433,A5)/B5 | H5: =SUMIFS(Питання!$N$2:$O$433,Питання!$A$2:$A$433,A5)/B5 | I5: =AVERAGEIFS(Питання!$T$2:$V$433,Питання!$A$2:$A$433,A5) | J5: =AVERAGEIFS(Питання!$U$2:$W$433,Питання!$A$2:$A$433,A5) | K5: =SUMIFS(Питання!$V$2:$X$433,Питання!$A$2:$A$433,A5)/B5 | L5: =AVERAGEIFS(Питання!$W$2:$Y$433,Питання!$A$2:$A$433,A5) | M5: =SUMIFS(Питання!$S$2:$T$433,Питання!$A$2:$A$433,A5)/B5 | N5: =SUMIFS(Питання!$Q$2:$R$433,Питання!$A$2:$A$433,A5)/B5

Sheet За лекціями
A1: Лекція | B1: M1 | C1: M2 | D1: M3 | E1: M4
A2: W01 | B2: =SUMIFS(Питання!$P$2:$Q$433,Питання!$A$2:$A$433,"M1",Питання!$B$2:$B$433,$A2) | C2: =SUMIFS(Питання!$P$2:$Q$433,Питання!$A$2:$A$433,"M2",Питання!$B$2:$B$433,$A2) | D2: =SUMIFS(Питання!$P$2:$Q$433,Питання!$A$2:$A$433,"M3",Питання!$B$2:$B$433,$A2) | E2: =SUMIFS(Питання!$P$2:$Q$433,Питання!$A$2:$A$433,"M4",Питання!$B$2:$B$433,$A2)
A3: W02 | B3: =SUMIFS(Питання!$P$2:$Q$433,Питання!$A$2:$A$433,"M1",Питання!$B$2:$B$433,$A3) | C3: =SUMIFS(Питання!$P$2:$Q$433,Питання!$A$2:$A$433,"M2",Питання!$B$2:$B$433,$A3) | D3: =SUMIFS(Питання!$P$2:$Q$433,Питання!$A$2:$A$433,"M3",Питання!$B$2:$B$433,$A3) | E3: =SUMIFS(Питання!$P$2:$Q$433,Питання!$A$2:$A$433,"M4",Питання!$B$2:$B$433,$A3)
A4: W03 | B4: =SUMIFS(Питання!$P$2:$Q$433,Питання!$A$2:$A$433,"M1",Питання!$B$2:$B$433,$A4) | C4: =SUMIFS(Питання!$P$2:$Q$433,Питання!$A$2:$A$433,"M2",Питання!$B$2:$B$433,$A4) | D4: =SUMIFS(Питання!$P$2:$Q$433,Питання!$A$2:$A$433,"M3",Питання!$B$2:$B$433,$A4) | E4: =SUMIFS(Питання!$P$2:$Q$433,Питання!$A$2:$A$433,"M4",Питання!$B$2:$B$433,$A4)
A5: D01 | B5: =SUMIFS(Питання!$P$2:$Q$433,Питання!$A$2:$A$433,"M1",Питання!$B$2:$B$433,$A5) | C5: =SUMIFS(Питання!$P$2:$Q$433,Питання!$A$2:$A$433,"M2",Питання!$B$2:$B$433,$A5) | D5: =SUMIFS(Питання!$P$2:$Q$433,Питання!$A$2:$A$433,"M3",Питання!$B$2:$B$433,$A5) | E5: =SUMIFS(Питання!$P$2:$Q$433,Питання!$A$2:$A$433,"M4",Питання!$B$2:$B$433,$A5)
A6: D02 | B6: =SUMIFS(Питання!$P$2:$Q$433,Питання!$A$2:$A$433,"M1",Питання!$B$2:$B$433,$A6) | C6: =SUMIFS(Питання!$P$2:$Q$433,Питання!$A$2:$A$433,"M2",Питання!$B$2:$B$433,$A6) | D6: =SUMIFS(Питання!$P$2:$Q$433,Питання!$A$2:$A$433,"M3",Питання!$B$2:$B$433,$A6) | E6: =SUMIFS(Питання!$P$2:$Q$433,Питання!$A$2:$A$433,"M4",Питання!$B$2:$B$433,$A6)
A7: D03 | B7: =SUMIFS(Питання!$P$2:$Q$433,Питання!$A$2:$A$433,"M1",Питання!$B$2:$B$433,$A7) | C7: =SUMIFS(Питання!$P$2:$Q$433,Питання!$A$2:$A$433,"M2",Питання!$B$2:$B$433,$A7) | D7: =SUMIFS(Питання!$P$2:$Q$433,Питання!$A$2:$A$433,"M3",Питання!$B$2:$B$433,$A7) | E7: =SUMIFS(Питання!$P$2:$Q$433,Питання!$A$2:$A$433,"M4",Питання!$B$2:$B$433,$A7)
A8: A01 | B8: =SUMIFS(Питання!$P$2:$Q$433,Питання!$A$2:$A$433,"M1",Питання!$B$2:$B$433,$A8) | C8: =SUMIFS(Питання!$P$2:$Q$433,Питання!$A$2:$A$433,"M2",Питання!$B$2:$B$433,$A8) | D8: =SUMIFS(Питання!$P$2:$Q$433,Питання!$A$2:$A$433,"M3",Питання!$B$2:$B$433,$A8) | E8: =SUMIFS(Питання!$P$2:$Q$433,Питання!$A$2:$A$433,"M4",Питання!$B$2:$B$433,$A8)
A9: A02 | B9: =SUMIFS(Питання!$P$2:$Q$433,Питання!$A$2:$A$433,"M1",Питання!$B$2:$B$433,$A9) | C9: =SUMIFS(Питання!$P$2:$Q$433,Питання!$A$2:$A$433,"M2",Питання!$B$2:$B$433,$A9) | D9: =SUMIFS(Питання!$P$2:$Q$433,Питання!$A$2:$A$433,"M3",Питання!$B$2:$B$433,$A9) | E9: =SUMIFS(Питання!$P$2:$Q$433,Питання!$A$2:$A$433,"M4",Питання!$B$2:$B$433,$A9)
A10: A03 | B10: =SUMIFS(Питання!$P$2:$Q$433,Питання!$A$2:$A$433,"M1",Питання!$B$2:$B$433,$A10) | C10: =SUMIFS(Питання!$P$2:$Q$433,Питання!$A$2:$A$433,"M2",Питання!$B$2:$B$433,$A10) | D10: =SUMIFS(Питання!$P$2:$Q$433,Питання!$A$2:$A$433,"M3",Питання!$B$2:$B$433,$A10) | E10: =SUMIFS(Питання!$P$2:$Q$433,Питання!$A$2:$A$433,"M4",Питання!$B$2:$B$433,$A10)
A11: Разом | B11: =SUM(B2:B10) | C11: =SUM(C2:C10) | D11: =SUM(D2:D10) | E11: =SUM(E2:E10)

Sheet Відхилені
A1: Конфігурація | B1: Лекція | C1: ID | D1: Цільовий рівень Блума | E1: Статус Критика | F1: Питання | G1: Ключ | H1: Дистрактор 1 | I1: Дистрактор 2 | J1: Дистрактор 3 | K1: F | L1: A | M1: P | N1: S | O1: Коментар арбітра
A2: M1 | B2: W01 | C2: b00_0 | D2: 1 | E2: m1_generated | F2: Що таке framework? | G2: Каркас для програми, що включає набір інструментів, бібліотек, модулів та методологію | H2: Мова програмування для створення веб-додатків | I2: Система управління базами даних | J2: Графічний редактор для дизайну інтерфейсів | K2: 1 | L2: 1 | M2: 1 | N2: 0 | O2: Знижено: No_Shortcuts=0 (ключ 11 слів проти 4.67 у дистракторів). Коментар моделі: Фактологічно ключ коректний: framework — це дійсно каркас/платформа, що включає набір інструментів, бібліотек, модулів та методологію розробки. Усі три дистрактори однозначно хибні та правдоподібні: мова програмування, СУБД і графічний редактор — реальні поняття зі сфери ІТ, які студент-початківець може сплутати з framework. Однак no_shortcuts_score = 0: ключ (11 слів) помітно довший за дистрактори (середня 4.67 слова), що автоматично виділяє його серед варіантів і є підказкою. Дистрактори слід розширити до порівнянної довжини або скоротити ключ.
A3: M1 | B3: W01 | C3: b00_4 | D3: 2 | E3: m1_generated | F3: Яка перевага Laravel перед «чистим PHP»? | G3: Код структурований, що робить його зрозумілим іншим розробникам | H3: Laravel не потребує знання PHP | I3: Laravel працює лише на Windows | J3: Laravel автоматично створює базу даних без SQL | K3: 1 | L3: 0 | M3: 1 | N3: 0 | O3: Знижено: No_Ambiguity=0; No_Shortcuts=0 (ключ 8 слів проти 5.67 у дистракторів; неоднорідний формат варіантів: KEY, D1, D2, D3). Коментар моделі: Фактологічно ключ коректний: Laravel як MVC-фреймворк справді структурує код і полегшує командну роботу. Дистрактори правдоподібні в межах теми (хибні, але типові помилкові уявлення про фреймворки). Однак є два дефекти. 1) no_shortcuts_score = 0: ключ помітно довший за дистрактори (8 слів проти середніх 5.67), що саме по собі є підказкою. 2) ambiguity_score = 0 через два порушення: (а) неоднорідність формату — слово «Laravel» (латиниця) присутнє в D1, D2, D3, але відсутнє в ключі, що виділяє ключ серед варіантів; (б) D2 містить категоричне слово «лише» у категоричному значенні, тоді як ключ його не містить — це додаткова підказка. Також D2 є очевидно хибним фактом (Laravel підтримує будь-яку ОС), що знижує конкурентність, але не виводить дистрактор за межі галузі.
A4: M1 | B4: W01 | C4: b00_6 | D4: 2 | E4: m1_generated | F4: Що таке Composer у контексті Laravel? | G4: Менеджер пакетів для встановлення та підключення залежностей | H4: Вбудований веб-сервер | I4: Шаблонізатор для HTML | J4: Система контролю версій | K4: 1 | L4: 1 | M4: 1 | N4: 0 | O4: Знижено: No_Shortcuts=0 (ключ 7 слів проти 2.67 у дистракторів). Коментар моделі: Фактологічно ключ коректний: Composer — менеджер залежностей (пакетів) для PHP/Laravel. Усі три дистрактори хибні й правдоподібні: вбудований веб-сервер (Artisan serve), шаблонізатор (Blade) та система контролю версій (Git) — реальні поняття зі сфери веб-розробки, які студент може сплутати. Однак no_shortcuts_score = 0: ключ містить 7 слів, тоді як середня довжина дистракторів — лише 2.67 слова, що є помітною підказкою. Неоднорідність формату: у D2 вжито латиницю («HTML»), тоді як в інших варіантах латиниці немає — проте це одна абревіатура, яка є загальновживаною і не виділяє варіант як підказку; format_mismatch не фіксується.
A5: M1 | B5: W02 | C5: b00_0 | D5: 1 | E5: m1_generated | F5: Що таке маршрутизація в Laravel? | G5: Спосіб зареєструвати можливий запит користувача до додатку | H5: Процес створення контролерів | I5: Механізм підключення шаблонів | J5: Спосіб передачі даних у види | K5: 1 | L5: 1 | M5: 1 | N5: 0 | O5: Знижено: No_Shortcuts=0 (ключ 7 слів проти 3.67 у дистракторів). Коментар моделі: Фактологічно ключ коректний: маршрутизація в Laravel — це реєстрація можливих HTTP-запитів (URI + метод) та їх обробників. Дистрактори правдоподібні й однозначно хибні: D1 (створення контролерів), D2 (підключення шаблонів), D3 (передача даних у види) — усі з тієї ж предметної галузі (Laravel/веброзробка) і не є правильними відповідями на питання про маршрутизацію. Однак no_shortcuts_score = 0: ключ (7 слів) помітно довший за дистрактори (середня 3.67 слова), що автоматично виділяє його серед варіантів і є підказкою для студента.
A6: M1 | B6: W02 | C6: b00_5 | D6: 2 | E6: m1_generated | F6: Як правильно оголосити необов'язковий параметр маршруту в Laravel? | G6: Route::get('user/{id?}', function($id = null) { return 'User '.$id; }) | H6: Route::get('user/{id}', function($id = null) { return 'User '.$id; }) | I6: Route::get('user/{id?}', function($id) { return 'User '.$id; }) | J6: Route::get('user/{id?}', function() { return 'User '.$id; }) | K6: 1 | L6: 0 | M6: 1 | N6: 1 | O6: Знижено: No_Ambiguity=0 (мовні помилки: options: надлишкова спільна частина). Коментар моделі: Фактологічно ключ коректний: у Laravel необов'язковий параметр маршруту позначається {id?} у шаблоні, а відповідний аргумент функції-замикання повинен мати значення за замовчуванням ($id = null). D1 — відсутній '?' у шаблоні, але є дефолт у функції; D2 — є '?' у шаблоні, але немає дефолту у функції; D3 — є '?' у шаблоні, але $id взагалі відсутній у параметрах функції (PHP видасть Notice/Warning при зверненні до невизначеної змінної). Усі дистрактори правдоподібні та належать до тієї самої предметної галузі. Однак ambiguity_score = 0: запитання містить посилання на джерело — ні, але є мовна проблема: у D3 функція не приймає $id як параметр, проте звертається до $id у тілі — це синтаксично некоректний PHP-код (undefined variable), що робить D3 очевидно хибним не через логіку маршрутизації Laravel, а через базову помилку PHP. Крім того, wording_issues: у всіх чотирьох варіантах є спільна частина 'Route::get('user/{id', function' та 'return 'User '.$id; })', що є надлишковим повтором у варіантах — дефект за критерієм Е. Через надлишковий повтор у варіантах додаємо wording_issues, що впливає на ambiguity_score = 0.
A7: M1 | B7: W02 | C7: b00_8 | D7: 3 | E7: m1_generated | F7: У якому порядку передаються параметри маршруту в контролер? | G7: У тому ж порядку, в якому вони задані в маршруті | H7: У зворотному порядку | I7: У порядку, визначеному назвами змінних | J7: У довільному порядку | K7: 1 | L7: 1 | M7: 1 | N7: 0 | O7: Знижено: No_Shortcuts=0 (ключ 10 слів проти 3.67 у дистракторів). Коментар моделі: no_shortcuts_score = 0: ключ (10 слів) помітно довший за дистрактори (середня 3.67 слова), що автоматично виділяє його серед варіантів. Фактологічно ключ коректний — у більшості MVC-фреймворків параметри маршруту передаються в контролер у тому порядку, в якому вони визначені в маршруті (хоча деякі фреймворки, як-от Laravel, також підтримують зіставлення за іменами; без конкретного джерела/фреймворку є певна неверифікованість). Дистрактори правдоподібні й однозначно хибні в загальному контексті. Мовних помилок не виявлено.
A8: M1 | B8: W03 | C8: b00_0 | D8: 1 | E8: m1_generated | F8: Що таке міграції в Laravel? | G8: Вбудований механізм для керування структурою бази даних | H8: Інструмент для написання SQL-запитів | I8: Бібліотека для роботи з формами | J8: Система кешування даних | K8: 1 | L8: 1 | M8: 1 | N8: 0 | O8: Знижено: No_Shortcuts=0 (ключ 7 слів проти 4 у дистракторів; неоднорідний формат варіантів: D1). Коментар моделі: Фактологічно ключ коректний: міграції в Laravel — це справді вбудований механізм керування структурою бази даних. Дистрактори правдоподібні й однозначно хибні. Однак no_shortcuts_score = 0 через дві причини: (1) ключ помітно довший за дистрактори (7 слів проти середніх 4), що автоматично виділяє його; (2) слово 'SQL' у D1 записане латиницею, тоді як решта варіантів — кирилицею, що порушує однорідність формату і може слугувати підказкою (D1 виглядає інакше). format_mismatch зафіксовано для D1.
A9: M1 | B9: W03 | C9: b00_10 | D9: 3 | E9: m1_generated | F9: Як застосувати колекції для фільтрації та трансформації даних? | G9: Використати filter() та map() з стрілочними функціями | H9: Використати where() та select() | I9: Використати sortBy() та pluck() | J9: Використати groupBy() та having() | K9: 1 | L9: 1 | M9: 1 | N9: 0 | O9: Знижено: No_Shortcuts=0 (ключ 7 слів проти 4 у дистракторів). Коментар моделі: no_shortcuts_score = 0: ключ містить 7 слів, тоді як дистрактори мають у середньому 4 слова — ключ помітно довший за дистрактори (метрики підтверджують). Уточнення «з стрілочними функціями» робить ключ виразно детальнішим і виділяє його серед варіантів. Фактологічно: filter() та map() є стандартними методами фільтрації та трансформації у колекціях (Laravel Collections, JavaScript Array тощо) — ключ коректний. Дистрактори правдоподібні: where()/select() асоціюються з ORM/SQL-запитами, sortBy()/pluck() — з сортуванням і вибіркою полів у Laravel Collections, groupBy()/having() — з групуванням у SQL/колекціях; усі належать до тієї самої предметної галузі. Двозначності немає: жоден дистрактор не є правильною відповіддю на питання «фільтрація ТА трансформація» одночасно.
A10: M1 | B10: W03 | C10: b00_3 | D10: 1 | E10: m1_generated | F10: Що таке Seeder у Laravel? | G10: Клас для завантаження початкових даних у базу даних | H10: Клас для створення міграцій | I10: Клас для роботи з колекціями | J10: Клас для побудови запитів | K10: 1 | L10: 1 | M10: 1 | N10: 0 | O10: Знижено: No_Shortcuts=0 (ключ 8 слів проти 4.33 у дистракторів). Коментар моделі: Фактологічно ключ коректний: Seeder у Laravel — це клас для завантаження початкових/тестових даних у базу даних. Усі три дистрактори однозначно хибні та правдоподібні: D1 (міграції), D2 (колекції), D3 (побудова запитів) — усі є реальними концепціями Laravel, які студент міг би сплутати. Однак no_shortcuts_score = 0: ключ містить 8 слів, тоді як середня довжина дистракторів — лише 4.33 слова, що є помітною різницею і може слугувати підказкою. Дистрактори варто розширити до порівнянної довжини (наприклад, 'Клас для створення та виконання міграцій бази даних').
A11: M1 | B11: W03 | C11: b00_4 | D11: 2 | E11: m1_generated | F11: Як можна пояснити призначення методу down() у міграції? | G11: Він містить інструкції для повернення системи у вихідний стан | H11: Він запускає міграцію | I11: Він створює нову таблицю | J11: Він видаляє всі дані з таблиці | K11: 1 | L11: 1 | M11: 1 | N11: 0 | O11: Знижено: No_Shortcuts=0 (ключ 9 слів проти 4.33 у дистракторів). Коментар моделі: Фактологічно ключ коректний: метод down() у міграціях (Laravel, Django та ін.) містить інструкції для відкату змін і повернення БД у попередній стан. Дистрактори правдоподібні й однозначно хибні: D1 описує запуск міграції (функція up()/migrate), D2 — конкретну дію up(), D3 — видалення даних (truncate), що не є призначенням down(). Слово «всі» у D3 вжите в нейтральному описовому контексті, не є категоричним у сенсі виключності. Однак no_shortcuts_score = 0: ключ (9 слів) помітно довший за дистрактори (середнє 4.33 слова), що автоматично виділяє його серед варіантів і є підказкою.
A12: M1 | B12: W03 | C12: b00_6 | D12: 2 | E12: m1_generated | F12: Як можна охарактеризувати метод timestamps() у міграції? | G12: Створює поля created_at і updated_at для автоматичного запису часу | H12: Створює поле для зберігання часу останнього входу | I12: Додає поле для зберігання дати народження | J12: Створює поле для зберігання часової зони | K12: 1 | L12: 1 | M12: 1 | N12: 0 | O12: Знижено: No_Shortcuts=0 (ключ 9 слів проти 6.33 у дистракторів; неоднорідний формат варіантів: KEY). Коментар моделі: Фактологічно ключ коректний: метод timestamps() у Laravel-міграціях створює поля created_at і updated_at. Дистрактори правдоподібні — усі стосуються зберігання часових даних у БД, що є типовою областю плутанини. Однозначність збережена: жоден дистрактор не є правильною відповіддю. Однак no_shortcuts_score = 0 з двох причин: (1) ключ помітно довший за дистрактори (9 слів проти середніх 6.33), що автоматично виділяє його; (2) ключ містить латиницю (назви полів created_at і updated_at), тоді як усі три дистрактори написані виключно кирилицею — це формальна неоднорідність, яка підказує правильну відповідь.
A13: M1 | B13: W03 | C13: b00_9 | D13: 3 | E13: m1_generated | F13: Як застосувати конструктор запитів для вибірки користувачів з певним ім'ям та сортуванням за email? | G13: DB::table('users')->where('name', 'John')->orderBy('email')->get(); | H13: DB::table('users')->where('name', '=', 'John')->orderBy('email', 'desc')->get(); | I13: DB::table('users')->where('name', 'John')->sortBy('email')->get(); | J13: DB::table('users')->where('name', 'John')->order('email')->get(); | K13: 1 | L13: 0 | M13: 1 | N13: 1 | O13: Знижено: No_Ambiguity=0. Коментар моделі: ambiguity_score = 0: D1 є технічно коректним синтаксисом Laravel Query Builder — where('name', '=', 'John') є еквівалентом скороченої форми, а orderBy('email', 'desc') виконує сортування за email (хоч і за спаданням). Оскільки питання не уточнює напрямок сортування ('asc' чи 'desc'), D1 також відповідає умові 'сортування за email', що робить завдання двозначним. Незалежний експерт також зазначив цю проблему. Дистрактори D2 (sortBy — метод колекції, не Query Builder) та D3 (order — неіснуючий метод) є правдоподібними помилками.
... A126: M4 | B126: A02 | C126: b10_0 | D126: 1 | E126: fixed_at_iter_3 | F126: Який метод штучного балансування вибірок застосовують для подолання дисбалансу класів у машинному навчанні? | G126: Метод синтетичного пересемплювання меншин. | H126: Коефіцієнт лінійної кореляції Пірсона. | I126: Логарифмічна трансформація ознак. | J126: Побудова ансамблю дерев рішень. | K126: 1 | L126: 1 | M126: 1 | N126: 0 | O126: Знижено: No_Shortcuts=0 (ключ повторює запитання: штучного балансування вибірок). Коментар моделі: no_shortcuts_score=0: ключ повторює запитання. У запитанні є «штучного балансування вибірок», а в ключі — «пересемплювання» (ресемплінг, зміна складу вибірки), тобто ключ семантично збігається з вирішальною частиною запитання. D1–D3 до балансування вибірок не стосуються, тому відповідь можна вгадати з самого запитання. Фактологія коректна: SMOTE (Synthetic Minority Over-sampling Technique) створює синтетичні приклади міноритарного класу й застосовується проти дисбалансу класів. Двозначності немає: кореляція Пірсона, логарифмічна трансформація ознак і ансамбль дерев рішень не є методами балансування вибірок. Ансамблі, наприклад Balanced Random Forest, можуть працювати з дисбалансом, але формулювання D3 («побудова ансамблю дерев рішень») не є методом штучного балансування вибірок. Дистрактори з тієї ж галузі (машинне навчання й аналіз даних), правдоподібні. Мовних помилок немає, надлишкових повторів у варіантах немає, формат однорідний.
